Aryan_Sindhi_101703110_outlier_removal/__init__.py
Aryan_Sindhi_101703110_outlier_removal/outlier.py
Aryan_Sindhi_101703110_outlier_removal-0.0.1.dist-info/LICENSE
Aryan_Sindhi_101703110_outlier_removal-0.0.1.dist-info/METADATA
Aryan_Sindhi_101703110_outlier_removal-0.0.1.dist-info/WHEEL
Aryan_Sindhi_101703110_outlier_removal-0.0.1.dist-info/top_level.txt
Aryan_Sindhi_101703110_outlier_removal-0.0.1.dist-info/RECORD
